{
  "trained_on": "2026-04-08T11:06:28.402050",
  "num_days": 262,
  "date_range": {
    "start": "2025-07-03",
    "end": "2026-04-07"
  },
  "feature_columns": [
    "nws_first",
    "nws_last",
    "nws_max",
    "nws_min",
    "nws_mean",
    "nws_spread",
    "nws_std",
    "nws_trend",
    "nws_count",
    "forecast_velocity",
    "forecast_acceleration",
    "accu_first",
    "accu_last",
    "accu_max",
    "accu_min",
    "accu_mean",
    "accu_spread",
    "accu_std",
    "accu_trend",
    "accu_count",
    "nws_accu_spread",
    "nws_accu_mean_diff",
    "day_of_year_sin",
    "day_of_year_cos",
    "month",
    "is_summer",
    "is_winter",
    "rolling_bias_7d",
    "rolling_bias_21d",
    "rolling_ml_error_7d",
    "has_accu_data"
  ],
  "residual_std": 1.8857592179130171,
  "bucket_method": "gaussian_from_regression",
  "base_source": "accu_last (fallback: nws_last)",
  "model_type": "HistGradientBoostingRegressor",
  "model_performance": {
    "cv_temperature_mae": 1.3,
    "cv_bucket_accuracy": 0.3023,
    "insample_temperature_mae": 0.81,
    "insample_bucket_accuracy": 0.4313,
    "residual_std": 1.89
  },
  "seasonal_performance": {
    "summer": {
      "days": 43,
      "insample_mae": 1.09
    },
    "fall": {
      "days": 91,
      "insample_mae": 0.73
    },
    "winter": {
      "days": 90,
      "insample_mae": 0.64
    },
    "spring": {
      "days": 38,
      "insample_mae": 1.07
    }
  },
  "top_features": [
    {
      "name": "accu_std",
      "importance": 0.2777
    },
    {
      "name": "day_of_year_cos",
      "importance": 0.1788
    },
    {
      "name": "rolling_bias_21d",
      "importance": 0.1614
    },
    {
      "name": "accu_trend",
      "importance": 0.141
    },
    {
      "name": "nws_accu_mean_diff",
      "importance": 0.0584
    },
    {
      "name": "nws_min",
      "importance": 0.0477
    },
    {
      "name": "nws_std",
      "importance": 0.0469
    },
    {
      "name": "nws_mean",
      "importance": 0.039
    },
    {
      "name": "accu_spread",
      "importance": 0.0339
    },
    {
      "name": "nws_count",
      "importance": 0.0326
    }
  ],
  "hyperparameters": {
    "max_iter": 300,
    "max_depth": 3,
    "learning_rate": 0.03,
    "min_samples_leaf": 20,
    "l2_regularization": 1.0,
    "max_leaf_nodes": 15,
    "cv_splits": 5
  }
}